{
  "info": [
    {
      "name": "mpa_22_dong_peds_demog",
      "classes": "data.frame",
      "size_mb": 0.0059
    }
  ],
  "json_preview": [
    {
      "ID": 1,
      "age": 12.0841,
      "wt": 39.6538,
      "ht": 138.0141,
      "bsa": 1.2629,
      "dose_bsa": 442.9418,
      "clcr1": 8.9156,
      "alb": 3.3222,
      "hgb": 10.2943,
      "gender": 1,
      "race": 0,
      "time": 0,
      "evid": 1,
      "cmt": 1,
      "dose": 559.3816,
      "amt": 559.3816,
      "ii": 12,
      "addl": 5,
      "clcr": 15.424
    },
    {
      "ID": 2,
      "age": 11.1003,
      "wt": 38.1689,
      "ht": 137.6915,
      "bsa": 1.8265,
      "dose_bsa": 444.5784,
      "clcr1": 6.2852,
      "alb": 4.1344,
      "hgb": 9.2787,
      "gender": 1,
      "race": 1,
      "time": 0,
      "evid": 1,
      "cmt": 1,
      "dose": 812.012,
      "amt": 812.012,
      "ii": 12,
      "addl": 5,
      "clcr": 10.8734
    },
    {
      "ID": 3,
      "age": 11.029,
      "wt": 39.9184,
      "ht": 136.273,
      "bsa": 1.8633,
      "dose_bsa": 443.6871,
      "clcr1": 8.8348,
      "alb": 3.267,
      "hgb": 11.5053,
      "gender": 1,
      "race": 1,
      "time": 0,
      "evid": 1,
      "cmt": 1,
      "dose": 826.7219,
      "amt": 826.7219,
      "ii": 12,
      "addl": 5,
      "clcr": 15.2841
    },
    {
      "ID": 4,
      "age": 11.5386,
      "wt": 39.835,
      "ht": 136.3579,
      "bsa": 1.5038,
      "dose_bsa": 445.4147,
      "clcr1": 7.5703,
      "alb": 3.6526,
      "hgb": 10.057,
      "gender": 0,
      "race": 1,
      "time": 0,
      "evid": 1,
      "cmt": 1,
      "dose": 669.822,
      "amt": 669.822,
      "ii": 12,
      "addl": 5,
      "clcr": 13.0967
    },
    {
      "ID": 5,
      "age": 13.6198,
      "wt": 38.5192,
      "ht": 137.9837,
      "bsa": 1.5939,
      "dose_bsa": 443.9655,
      "clcr1": 7.467,
      "alb": 4.2334,
      "hgb": 11.5552,
      "gender": 1,
      "race": 0,
      "time": 0,
      "evid": 1,
      "cmt": 1,
      "dose": 707.6469,
      "amt": 707.6469,
      "ii": 12,
      "addl": 5,
      "clcr": 12.918
    },
    {
      "ID": 6,
      "age": 13.6903,
      "wt": 39.9346,
      "ht": 136.517,
      "bsa": 1.4286,
      "dose_bsa": 443.8516,
      "clcr1": 6.3269,
      "alb": 2.8008,
      "hgb": 11.239,
      "gender": 0,
      "race": 0,
      "time": 0,
      "evid": 1,
      "cmt": 1,
      "dose": 634.1084,
      "amt": 634.1084,
      "ii": 12,
      "addl": 5,
      "clcr": 10.9456
    }
  ],
  "r_preview": ["{\"type\":\"list\",\"attributes\":{\"names\":{\"type\":\"character\",\"attributes\":{},\"value\":[\"ID\",\"age\",\"wt\",\"ht\",\"bsa\",\"dose_bsa\",\"clcr1\",\"alb\",\"hgb\",\"gender\",\"race\",\"time\",\"evid\",\"cmt\",\"dose\",\"amt\",\"ii\",\"addl\",\"clcr\"]},\"row.names\":{\"type\":\"integer\",\"attributes\":{},\"value\":[1,2,3,4,5,6]},\"class\":{\"type\":\"character\",\"attributes\":{},\"value\":[\"data.frame\"]}},\"value\":[{\"type\":\"integer\",\"attributes\":{},\"value\":[1,2,3,4,5,6]},{\"type\":\"double\",\"attributes\":{},\"value\":[12.08411729,11.10027211,11.02899732,11.53859568,13.61983292,13.69029727]},{\"type\":\"double\",\"attributes\":{},\"value\":[39.65377287,38.16893592,39.91842479,39.83503045,38.51919966,39.93455446]},{\"type\":\"double\",\"attributes\":{},\"value\":[138.01406298,137.69154887,136.27298828,136.35790736,137.98370667,136.51696027]},{\"type\":\"double\",\"attributes\":{},\"value\":[1.26287841,1.82647639,1.8632991,1.50381636,1.59392296,1.42864939]},{\"type\":\"double\",\"attributes\":{},\"value\":[442.94180786,444.57842289,443.68714728,445.41472584,443.96553875,443.85162524]},{\"type\":\"double\",\"attributes\":{},\"value\":[8.91560126,6.28521743,8.83476052,7.57033983,7.46703904,6.32694002]},{\"type\":\"double\",\"attributes\":{},\"value\":[3.32223939,4.13439146,3.26698044,3.65257761,4.23336414,2.80076414]},{\"type\":\"double\",\"attributes\":{},\"value\":[10.29425166,9.27871375,11.50529921,10.05700102,11.555215,11.23902672]},{\"type\":\"double\",\"attributes\":{},\"value\":[1,1,1,0,1,0]},{\"type\":\"double\",\"attributes\":{},\"value\":[0,1,1,1,0,0]},{\"type\":\"double\",\"attributes\":{},\"value\":[0,0,0,0,0,0]},{\"type\":\"double\",\"attributes\":{},\"value\":[1,1,1,1,1,1]},{\"type\":\"double\",\"attributes\":{},\"value\":[1,1,1,1,1,1]},{\"type\":\"double\",\"attributes\":{},\"value\":[559.38164385,812.01199129,826.72186394,669.82195067,707.64686464,634.108354]},{\"type\":\"double\",\"attributes\":{},\"value\":[559.38164385,812.01199129,826.72186394,669.82195067,707.64686464,634.108354]},{\"type\":\"double\",\"attributes\":{},\"value\":[12,12,12,12,12,12]},{\"type\":\"double\",\"attributes\":{},\"value\":[5,5,5,5,5,5]},{\"type\":\"double\",\"attributes\":{},\"value\":[15.42399018,10.87342616,15.2841357,13.0966879,12.91797755,10.94560623]}]}"],
  "time": ["2017-04-20 21:40:15"]
}
